{"cameraMode":{"drawMode":0,"name":"Shaded","section":"Shading Mode"},"sceneLighting":true,"audioPlay":false,"sceneViewState":{"showFog":true,"showMaterialUpdate":false,"showSkybox":true,"showFlares":true,"showImageEffects":true,"showParticleSystems":true},"in2DMode":false,"pivot":{"x":0.2784419059753418,"y":-1.0673179626464844,"z":7.472081184387207},"rotation":{"x":-0.14352300763130189,"y":0.7698146104812622,"z":-0.18619291484355927,"w":-0.5933961272239685},"size":113.6059341430664,"orthographic":false}